myLib/__init__.py
myLib/datastructures/__init__.py
myLib/datastructures/linear/LLQueue.py
myLib/datastructures/linear/LLStack.py
myLib/datastructures/linear/__init__.py
myLib/datastructures/linear/doublyCLL.py
myLib/datastructures/linear/doublyLL.py
myLib/datastructures/linear/singlyCLL.py
myLib/datastructures/linear/singlyLL.py
myLib/datastructures/nodes/DNode.py
myLib/datastructures/nodes/SNode.py
myLib/datastructures/nodes/TNode.py
myLib/datastructures/nodes/__init__.py
myLib/datastructures/trees/AVL.py
myLib/datastructures/trees/BST.py
myLib/datastructures/trees/__init__.py
anita_maheen_338_package-1.0.dist-info/METADATA
anita_maheen_338_package-1.0.dist-info/WHEEL
anita_maheen_338_package-1.0.dist-info/top_level.txt
anita_maheen_338_package-1.0.dist-info/RECORD
