Metadata-Version: 2.1
Name: anita-maheen-338-package
Version: 1.0
Summary: a simple library providing various datastructures
Author: Anita John, Maheen Raza
Author-email: anita.john@ucalgary.ca, maheen.raza@ucalgary.ca
